pylsd/__init__.py
pylsd/lsd.py
pylsd/bindings/__init__.py
pylsd/bindings/lsd_ctypes.py
pylsd/lib/darwin/liblsd.dylib
pylsd/lib/linux/liblsd.so
pylsd/lib/win32/x64/lsd.dll
py3lsd-0.0.1.dist-info/LICENSE
py3lsd-0.0.1.dist-info/METADATA
py3lsd-0.0.1.dist-info/WHEEL
py3lsd-0.0.1.dist-info/top_level.txt
py3lsd-0.0.1.dist-info/RECORD
