Metadata-Version: 2.1
Name: py3lsd
Version: 0.0.1
Summary: py3lsd is the python bindings for LSD - Line Segment Detector
Home-page: https://github.com/dakun333/py3lsd
Author: ShiKun Zhang
Author-email: m15326861966@163.com
License: BSD
Keywords: LSD
Platform: UNKNOWN
